Metadata-Version: 2.1
Name: twitter-trending-scraper-python
Version: 1.0.0
Summary: A python library to scrape trending keywords from twitter automatically.
Home-page: https://twitter-api.datakund.com/en/latest/
Author: DataKund
Author-email: datakund@gmail.com
License: Apache License 2.0
Keywords: twitter python bot_studio scraper login trending hashtags data web-scraping
Platform: UNKNOWN
